{
  "monthlyCollections": "₹1,84,000",
  "pendingRent": "₹4,800",
  "expenses": "₹42,000",
  "profit": "₹1,42,000",
  "invoices": [
    { "invoiceId": "INV-2026-004", "date": "2026-07-01", "amount": "₹4,200", "plan": "Pro Plan", "status": "paid" },
    { "invoiceId": "INV-2026-003", "date": "2026-06-01", "amount": "₹4,200", "plan": "Pro Plan", "status": "paid" }
  ],
  "paymentTimeline": [
    { "id": 1, "title": "Subscription Paid", "description": "₹4,200 credited for July cycle via Razorpay", "timestamp": "July 1, 2026", "badgeText": "Paid", "badgeVariant": "success" },
    { "id": 2, "title": "Warden Payout", "description": "₹12,000 wage transaction logged by owner", "timestamp": "June 30, 2026", "badgeText": "Expense", "badgeVariant": "warning" }
  ],
  "collectionTrends": [
    { "month": "Jan", "amount": 140000 },
    { "month": "Feb", "amount": 155000 },
    { "month": "Mar", "amount": 162000 },
    { "month": "Apr", "amount": 170000 },
    { "month": "May", "amount": 176000 },
    { "month": "Jun", "amount": 184000 }
  ]
}
